pywget/__init__.py
pywget/__main__.py
pywget/__version__.py
pywget/wget.py
pywget-0.31.data/data/LICENSE.rst
pywget-0.31.data/data/README.rst
pywget-0.31.data/data/__version__.py
pywget-0.31.dist-info/LICENSE.rst
pywget-0.31.dist-info/METADATA
pywget-0.31.dist-info/WHEEL
pywget-0.31.dist-info/entry_points.txt
pywget-0.31.dist-info/top_level.txt
pywget-0.31.dist-info/RECORD
