Metadata-Version: 2.1
Name: pywget
Version: 0.31
Summary: command line wget downloader alternative, this can be module/package
Home-page: https://bitbucket.org/licface/pywget
Author: Hadi Cahyadi LD
Author-email: cumulus13@gmail.com
Maintainer: cumulus13 Team
Maintainer-email: cumulus13@gmail.com
License: BSD
Project-URL: Documentation, https://bitbucket.org/licface/pywget
Project-URL: Code, https://bitbucket.org/licface/pywget
Platform: UNKNOWN
Classifier: Development Status :: 5 - Production/Stable
Classifier: Intended Audience :: Developers
Classifier: License :: OSI Approved :: BSD License
Classifier: Operating System :: OS Independent
Classifier: Programming Language :: Python
Classifier: Programming Language :: Python :: 2
Classifier: Programming Language :: Python :: 2.7
Classifier: Programming Language :: Python :: 3
Classifier: Programming Language :: Python :: 3.4
Classifier: Programming Language :: Python :: 3.5
Classifier: Programming Language :: Python :: 3.6
Classifier: Programming Language :: Python :: 3.7
Requires-Python: >=2.7, !=3.0.*, !=3.1.*, !=3.2.*, !=3.3.*
